py_combinator-0.2.0.dist-info/METADATA
py_combinator-0.2.0.dist-info/WHEEL
py_combinator/__init__.py
py_combinator/__init__.pyi
py_combinator/_py_combinator.cpython-313t-arm-linux-gnueabihf.so
py_combinator/py.typed
py_combinator/wrappers.py
py_combinator-0.2.0.dist-info/RECORD
